Metadata-Version: 2.1
Name: pacotepypi123
Version: 0.0.1
Summary: Pacote python para exibir número de 1 a 9
Home-page: https://github.com/aAmoraP?tab=repositories
Author: Amora Sofia da Paixão
Author-email: amorapaixaodev@gmail.com
License: MIT License
Keywords: Pacote
License-File: LICENSE
